Qwael/DRİVE.py
Qwael/DoIP.py
Qwael/EasyWeb.py
Qwael/MultiDB.py
Qwael/Multidata.py
Qwael/__init__.py
Qwael/filesz.py
Qwael/pgif.py
qwael-4.0.4.2.dist-info/licenses/LICENSE
qwael-4.0.4.2.dist-info/METADATA
qwael-4.0.4.2.dist-info/WHEEL
qwael-4.0.4.2.dist-info/top_level.txt
qwael-4.0.4.2.dist-info/RECORD
