Metadata-Version: 2.4
Name: Qwael
Version: 4.0.4.2
Summary: Qwael: İşlevsel ve kolaylaştırılmış Python kütüphanesi
Author: Bedirhan
Author-email: bedirhan.oytpass@gmail.com
License: MIT
Keywords: Kolay kod,drive,basitleştirilmiş
Classifier: License :: OSI Approved :: MIT License
Classifier: Programming Language :: Python :: 3
Classifier: Programming Language :: Python :: 3.6
Classifier: Programming Language :: Python :: 3.7
Classifier: Programming Language :: Python :: 3.8
Classifier: Programming Language :: Python :: 3.9
Classifier: Programming Language :: Python :: 3.10
License-File: LICENSE
Requires-Dist: google-api-python-client
Requires-Dist: google-auth
Requires-Dist: google-auth-oauthlib
Requires-Dist: google-auth-httplib2
Requires-Dist: Pillow
Requires-Dist: flask
Requires-Dist: pyyaml
Requires-Dist: requests
Dynamic: author
Dynamic: author-email
Dynamic: classifier
Dynamic: description
Dynamic: description-content-type
Dynamic: keywords
Dynamic: license
Dynamic: license-file
Dynamic: requires-dist
Dynamic: summary
